tests/__init__.py
tests/test_filter.py
thaidp/__init__.py
thaidp/clean.py
thaidp/filter.py
thaidp/gen.py
thaidp/rules.py
thaidp-0.1.dev0.dist-info/LICENSE
thaidp-0.1.dev0.dist-info/METADATA
thaidp-0.1.dev0.dist-info/WHEEL
thaidp-0.1.dev0.dist-info/top_level.txt
thaidp-0.1.dev0.dist-info/RECORD
